daviswx/__init__.py
daviswx/getobs.py
daviswx-0.0.1.data/data/external/remserial
daviswx-0.0.1.data/data/external/vproweather
daviswx-0.0.1.dist-info/METADATA
daviswx-0.0.1.dist-info/WHEEL
daviswx-0.0.1.dist-info/top_level.txt
daviswx-0.0.1.dist-info/RECORD
