Metadata-Version: 2.1
Name: daviswx
Version: 0.0.1
Summary: Tools for accessing Davis Vantage Pro II
Home-page: https://github.com/krasting/daviswx
Author: John Krasting
Author-email: krasting@gmail.com
License: UNKNOWN
Platform: UNKNOWN
Classifier: Programming Language :: Python :: 3
Classifier: License :: OSI Approved :: MIT License
Classifier: Operating System :: OS Independent
